mds_sm_pycounts/__init__.py
mds_sm_pycounts/mds_sm_pycounts.py
mds_sm_pycounts/plotting.py
mds_sm_pycounts-0.1.0.dist-info/LICENSE
mds_sm_pycounts-0.1.0.dist-info/METADATA
mds_sm_pycounts-0.1.0.dist-info/WHEEL
mds_sm_pycounts-0.1.0.dist-info/RECORD
